{"gtabs":[{"panes":[{"ptabs":[{"history":[{"dir":"/home/lucas/Engenharia_de_Computacao/3_periodo/AOCO/Teams","file":"2020-10-20_aula_10.mp4","relpos":16,"ts":1604887342},{"dir":"/home/lucas/Engenharia_de_Computacao/3_periodo","file":"AEDA","relpos":1,"ts":1604887342},{"dir":"/home/lucas/Engenharia_de_Computacao/3_periodo/AEDA","file":"teams","relpos":7,"ts":1604887342},{"dir":"/home/lucas/Engenharia_de_Computacao/3_periodo/AEDA/teams","file":"2020-10-22.mp4","relpos":14,"ts":1604887342},{"dir":"/home/lucas/Engenharia_de_Computacao/3_periodo/AEDA","file":"teams","relpos":7,"ts":1604887342},{"dir":"/home/lucas/Engenharia_de_Computacao/3_periodo","file":"AEDA","relpos":1,"ts":1604887342},{"dir":"/home/lucas/Engenharia_de_Computacao","file":"3_periodo","relpos":3,"ts":1604887342},{"dir":"/home/lucas/Engenharia_de_Computacao/3_periodo","file":"MNCMP","relpos":6,"ts":1604887342},{"dir":"/home/lucas/Engenharia_de_Computacao/3_periodo/MNCMP","file":"teams","relpos":5,"ts":1604887342},{"dir":"/home/lucas/Engenharia_de_Computacao/3_periodo/MNCMP/teams","file":"2020-11-05.mp4","relpos":8,"ts":1604887342},{"dir":"/home/lucas/Engenharia_de_Computacao/3_periodo","file":"AOCO","relpos":2,"ts":1604887342},{"dir":"/home/lucas/Engenharia_de_Computacao/3_periodo/AOCO","file":"Teams","relpos":3,"ts":1604887342},{"dir":"/home/lucas/Engenharia_de_Computacao/3_periodo/AOCO/Teams","file":"2020-10-20_aula_10.mp4","relpos":16,"ts":1604887342},{"dir":"/home/lucas/Engenharia_de_Computacao/3_periodo/AEDA/teams","file":"2020-10-22.mp4","relpos":14,"ts":1604928436},{"dir":"/home/lucas/.config","file":"mimeapps.list","relpos":34,"ts":1604956876},{"dir":"/home/lucas","file":".cache","relpos":1,"ts":1604956876},{"dir":"/home/lucas/.cache","file":"event-sound-cache.tdb.0532d1e3cd4f41358e877e9a2646a26d.x86_64-pc-linux-gnu","relpos":28,"ts":1604956876},{"dir":"/home/lucas/.config","file":"mimeapps.list","relpos":34,"ts":1604956876},{"dir":"/home/lucas","file":".cache","relpos":1,"ts":1604956876},{"dir":"/home/lucas/.cache","file":"event-sound-cache.tdb.0532d1e3cd4f41358e877e9a2646a26d.x86_64-pc-linux-gnu","relpos":28,"ts":1604956876},{"dir":"/home/lucas/.config","file":"mimeapps.list","relpos":34,"ts":1604956876},{"dir":"/home/lucas","file":".cache","relpos":1,"ts":1604956876},{"dir":"/home/lucas/.cache","file":"event-sound-cache.tdb.0532d1e3cd4f41358e877e9a2646a26d.x86_64-pc-linux-gnu","relpos":28,"ts":1604956876},{"dir":"/home/lucas/.config","file":"mimeapps.list","relpos":34,"ts":1604956876},{"dir":"/home/lucas","file":".cache","relpos":1,"ts":1604956876},{"dir":"/home/lucas/.cache","file":"event-sound-cache.tdb.0532d1e3cd4f41358e877e9a2646a26d.x86_64-pc-linux-gnu","relpos":28,"ts":1604956876},{"dir":"/home/lucas","file":"Downloads","relpos":3,"ts":1604957075},{"dir":"/home/lucas/Downloads","file":"Aula4.pdf","relpos":8,"ts":1604972867},{"dir":"/home/lucas","file":"Videos","relpos":6,"ts":1604972867},{"dir":"/home/lucas/Downloads","file":"Aula4.pdf","relpos":8,"ts":1604972867},{"dir":"/home/lucas","file":"Videos","relpos":6,"ts":1604972867},{"dir":"/home/lucas/Videos","file":"paraNestor.mp4","relpos":1,"ts":1605027218},{"dir":"/home/lucas","file":"scrot","relpos":9,"ts":1605027218},{"dir":"/home/lucas/scrot","file":"..","relpos":0,"ts":1605027218},{"dir":"/home/lucas","file":"servo","relpos":10,"ts":1605027218},{"dir":"/home/lucas/servo","file":"..","relpos":0,"ts":1605027218},{"dir":"/home/lucas/Videos","file":"paraNestor.mp4","relpos":1,"ts":1605027218},{"dir":"/home/lucas","file":"scrot","relpos":9,"ts":1605027218},{"dir":"/home/lucas/scrot","file":"..","relpos":0,"ts":1605027218},{"dir":"/home/lucas","file":"servo","relpos":10,"ts":1605027218},{"dir":"/home/lucas/servo","file":"..","relpos":0,"ts":1605027218},{"dir":"/home/lucas/kazam","file":"bin","relpos":1,"ts":1605032410},{"dir":"/home/lucas/kazam/bin","file":"..","relpos":0,"ts":1605032410},{"dir":"/home/lucas/kazam","file":"data","relpos":2,"ts":1605032410},{"dir":"/home/lucas","file":"kazam","relpos":8,"ts":1605032410},{"dir":"/home/lucas/kazam","file":"bin","relpos":1,"ts":1605032410},{"dir":"/","file":"home","relpos":4,"ts":1605042576},{"dir":"/home/lucas","file":"Desktop","relpos":1,"ts":1605042576},{"dir":"/home/lucas/Desktop","file":"prova","relpos":2,"ts":1605042576},{"dir":"/home/lucas/Desktop/prova","file":"Scan_1.pdf","relpos":2,"ts":1605042576},{"dir":"/home/lucas/Desktop","file":"dotfiles","relpos":1,"ts":1605042576},{"dir":"/home/lucas/Desktop/dotfiles","file":"..","relpos":0,"ts":1605042576},{"dir":"/home/lucas/Desktop","file":"dotfiles","relpos":1,"ts":1605042576},{"dir":"/home/lucas","file":"Desktop","relpos":1,"ts":1605042576},{"dir":"/home/lucas/Desktop","file":"prova","relpos":2,"ts":1605042576},{"dir":"/home/lucas","file":"kazam","relpos":8,"ts":1605042576},{"dir":"/home/lucas/kazam","file":"..","relpos":0,"ts":1605042576},{"dir":"/home/lucas","file":"scripts","relpos":8,"ts":1605042576},{"dir":"/home/lucas/scripts","file":"luke","relpos":11,"ts":1605042576},{"dir":"/home/lucas","file":"Interpola√ß√£o_Polinomial_Newton.pdf","relpos":14,"ts":1605047985},{"dir":"/home/lucas/Downloads","file":"ffmpeg-git-20201104-amd64-static","relpos":2,"ts":1605047985},{"dir":"/home/lucas/Downloads/ffmpeg-git-20201104-amd64-static","file":"ffmpeg","relpos":5,"ts":1605047985},{"dir":"/home/lucas/Downloads","file":"ffmpeg-git-20201104-amd64-static","relpos":2,"ts":1605047985},{"dir":"/home/lucas","file":"scripts","relpos":8,"ts":1605047985},{"dir":"/home/lucas/scripts","file":"luke","relpos":11,"ts":1605094557},{"dir":"/home/lucas","file":"scripts","relpos":8,"ts":1605094557},{"dir":"/home/lucas/scripts","file":"luke","relpos":11,"ts":1605094557},{"dir":"/home/lucas","file":"Videos","relpos":6,"ts":1605094557},{"dir":"/home/lucas/Videos","file":"paraNestor.mp4","relpos":1,"ts":1605094557},{"dir":"/home/lucas","file":"Images","relpos":5,"ts":1605094557},{"dir":"/home/lucas/Images","file":"arch.png","relpos":8,"ts":1605094557},{"dir":"/home/lucas","file":"scripts","relpos":8,"ts":1605094557},{"dir":"/home/lucas/scripts","file":"fsr","relpos":8,"ts":1605094557},{"dir":"/home/lucas","file":"scripts","relpos":8,"ts":1605095706},{"dir":"/home/lucas/scripts","file":"luke","relpos":11,"ts":1605095706},{"dir":"/home/lucas","file":"scripts","relpos":8,"ts":1605095706},{"dir":"/home/lucas/scripts","file":"fsr","relpos":8,"ts":1605096290},{"dir":"/home/lucas","file":"Desktop","relpos":1,"ts":1605096290},{"dir":"/home/lucas/Desktop","file":"dotfiles","relpos":1,"ts":1605096290},{"dir":"/home/lucas/Desktop/dotfiles","file":"home-user","relpos":2,"ts":1605096290},{"dir":"/home/lucas/Desktop/dotfiles/home-user","file":"scripts","relpos":1,"ts":1605096290},{"dir":"/home/lucas/Desktop/dotfiles/home-user/scripts","file":"fsr","relpos":8,"ts":1605096290},{"dir":"/home/lucas/Desktop/dotfiles/home-user","file":".config","relpos":1,"ts":1605096290},{"dir":"/home/lucas/Desktop/dotfiles/home-user/.config","file":"alacritty","relpos":1,"ts":1605096290},{"dir":"/home/lucas/Desktop/dotfiles/home-user/.config/alacritty","file":"alacritty.yml","relpos":1,"ts":1605096290},{"dir":"/home/lucas/Desktop/dotfiles/home-user/.config","file":"mpv","relpos":2,"ts":1605096290},{"dir":"/home/lucas/Desktop/dotfiles/home-user/.config/mpv","file":"input.conf","relpos":1,"ts":1605096290},{"dir":"/home/lucas/Desktop/dotfiles/home-user/.config","file":"nvim","relpos":3,"ts":1605096290},{"dir":"/home/lucas/Desktop/dotfiles/home-user/.config/nvim","file":"init.vim","relpos":2,"ts":1605096290},{"dir":"/home/lucas/Desktop/dotfiles/home-user/.config","file":"vifm","relpos":4,"ts":1605096290},{"dir":"/home/lucas/Desktop/dotfiles/home-user/.config/vifm","file":"vifmrc","relpos":4,"ts":1605096290},{"dir":"/home/lucas/Desktop/dotfiles/home-user/.config","file":"zathura","relpos":5,"ts":1605096290},{"dir":"/home/lucas/Desktop/dotfiles/home-user/.config/zathura","file":"zathurarc","relpos":1,"ts":1605096290},{"dir":"/home/lucas/Desktop/dotfiles/home-user/.config","file":"zathura","relpos":5,"ts":1605096290},{"dir":"/home/lucas/Desktop/dotfiles/home-user","file":".vimrc","relpos":7,"ts":1605096290},{"dir":"/home/lucas/Desktop/dotfiles","file":"home-user","relpos":3,"ts":1605096290},{"dir":"/home/lucas/Desktop/dotfiles/home-user","file":".vim-after-ftplugin","relpos":2,"ts":1605096290},{"dir":"/home/lucas/Desktop/dotfiles/home-user/.vim-after-ftplugin","file":"..","relpos":0,"ts":1605096290},{"dir":"/home/lucas/Desktop/dotfiles/home-user","file":"scripts","relpos":3,"ts":1605096290},{"dir":"/home/lucas/Desktop/dotfiles/home-user/scripts","file":"fsr","relpos":8,"ts":1605096290}],"filters":{"invert":true,"dot":false,"manual":"","auto":""},"last-location":"/home/lucas/Desktop/dotfiles/home-user/scripts","sorting":[1,2],"preview":false}]},{"ptabs":[{"history":[{"dir":"/home/lucas/Engenharia_de_Computacao/3_periodo/AEDA","file":"teams","relpos":7,"ts":1604887342},{"dir":"/home/lucas/Engenharia_de_Computacao/3_periodo/AEDA/teams","file":"..","relpos":0,"ts":1604887342},{"dir":"/home/lucas/Engenharia_de_Computacao/3_periodo/AEDA","file":"3-metodos_de_ordenacao","relpos":4,"ts":1604887342},{"dir":"/home/lucas/Engenharia_de_Computacao/3_periodo/AEDA/3-metodos_de_ordenacao","file":"..","relpos":0,"ts":1604887342},{"dir":"/home/lucas/Engenharia_de_Computacao/3_periodo/AEDA","file":"2-estruturas_dinamicas","relpos":3,"ts":1604887342},{"dir":"/home/lucas/Engenharia_de_Computacao/3_periodo/AEDA/2-estruturas_dinamicas","file":"Etapa_2","relpos":1,"ts":1604887342},{"dir":"/home/lucas/Engenharia_de_Computacao/3_periodo/AEDA/2-estruturas_dinamicas/Etapa_2","file":"src","relpos":1,"ts":1604887342},{"dir":"/home/lucas/Engenharia_de_Computacao/3_periodo/AEDA/2-estruturas_dinamicas/Etapa_2/src","file":"main.cpp","relpos":13,"ts":1604887342},{"dir":"/home/lucas","file":"Interpola√ß√£o_Polinomial_Newton.pdf","relpos":14,"ts":1604887342},{"dir":"/home/lucas/Engenharia_de_Computacao/3_periodo","file":"AEDA","relpos":1,"ts":1604887342},{"dir":"/home/lucas/Engenharia_de_Computacao/3_periodo/AEDA","file":"2-estruturas_dinamicas","relpos":3,"ts":1604887342},{"dir":"/home/lucas/Engenharia_de_Computacao/3_periodo/AEDA/2-estruturas_dinamicas","file":"Pratica_3-Etapa_2_-_Lucas_Martins_Soares","relpos":2,"ts":1604887342},{"dir":"/home/lucas/Engenharia_de_Computacao/3_periodo/AEDA/2-estruturas_dinamicas/Pratica_3-Etapa_2_-_Lucas_Martins_Soares","file":"src","relpos":1,"ts":1604887342},{"dir":"/home/lucas/Engenharia_de_Computacao/3_periodo/AEDA/2-estruturas_dinamicas","file":"backup","relpos":3,"ts":1604887342},{"dir":"/home/lucas/Engenharia_de_Computacao/3_periodo/AEDA","file":"1-estruturas_estaticas","relpos":2,"ts":1604887342},{"dir":"/home/lucas/Engenharia_de_Computacao/3_periodo/AEDA/1-estruturas_estaticas","file":"..","relpos":0,"ts":1604887342},{"dir":"/home/lucas/Engenharia_de_Computacao/3_periodo/AEDA","file":"2-estruturas_dinamicas","relpos":3,"ts":1604887342},{"dir":"/home/lucas/Engenharia_de_Computacao/3_periodo/AEDA/2-estruturas_dinamicas","file":"ListaPilhaFila","relpos":2,"ts":1604887342},{"dir":"/home/lucas/Engenharia_de_Computacao/3_periodo/AEDA","file":"3-metodos_de_ordenacao","relpos":4,"ts":1604887342},{"dir":"/home/lucas/Engenharia_de_Computacao/3_periodo/AEDA/3-metodos_de_ordenacao","file":"..","relpos":0,"ts":1604887342},{"dir":"/home/lucas/Engenharia_de_Computacao/3_periodo/AEDA","file":"2-estruturas_dinamicas","relpos":3,"ts":1604887342},{"dir":"/home/lucas/Engenharia_de_Computacao/3_periodo/AEDA/2-estruturas_dinamicas","file":"ListaPilhaFila","relpos":2,"ts":1604887342},{"dir":"/home/lucas/Engenharia_de_Computacao/3_periodo/AEDA","file":"0-analise_assintotica","relpos":1,"ts":1604887342},{"dir":"/home/lucas/Engenharia_de_Computacao/3_periodo/AEDA/0-analise_assintotica","file":"TT01","relpos":1,"ts":1604887342},{"dir":"/home/lucas/Engenharia_de_Computacao/3_periodo/AEDA","file":"0-analise_assintotica","relpos":1,"ts":1604887342},{"dir":"/home/lucas/Engenharia_de_Computacao/3_periodo/AEDA/0-analise_assintotica","file":"TT01","relpos":1,"ts":1604887342},{"dir":"/home/lucas/Engenharia_de_Computacao/3_periodo/AEDA","file":"teams","relpos":7,"ts":1604887342},{"dir":"/home/lucas/Engenharia_de_Computacao/3_periodo/AEDA/teams","file":"..","relpos":0,"ts":1604887342},{"dir":"/home/lucas/Engenharia_de_Computacao/3_periodo/AEDA","file":"3-metodos_de_ordenacao","relpos":4,"ts":1604887342},{"dir":"/home/lucas/Engenharia_de_Computacao/3_periodo/AEDA/3-metodos_de_ordenacao","file":"..","relpos":0,"ts":1604887342},{"dir":"/home/lucas/Engenharia_de_Computacao/3_periodo/AEDA","file":"2-estruturas_dinamicas","relpos":3,"ts":1604887342},{"dir":"/home/lucas/Engenharia_de_Computacao/3_periodo/AEDA/2-estruturas_dinamicas","file":"Etapa_2","relpos":1,"ts":1604887342},{"dir":"/home/lucas/Engenharia_de_Computacao/3_periodo/AEDA/2-estruturas_dinamicas/Etapa_2","file":"src","relpos":1,"ts":1604887342},{"dir":"/home/lucas/Engenharia_de_Computacao/3_periodo/AEDA/2-estruturas_dinamicas/Etapa_2/src","file":"main.cpp","relpos":13,"ts":1604887342},{"dir":"/home/lucas","file":"Interpola√ß√£o_Polinomial_Newton.pdf","relpos":14,"ts":1604887342},{"dir":"/home/lucas/Engenharia_de_Computacao/3_periodo","file":"AEDA","relpos":1,"ts":1604887342},{"dir":"/home/lucas/Engenharia_de_Computacao/3_periodo/AEDA","file":"2-estruturas_dinamicas","relpos":3,"ts":1604887342},{"dir":"/home/lucas/Engenharia_de_Computacao/3_periodo/AEDA/2-estruturas_dinamicas","file":"Pratica_3-Etapa_2_-_Lucas_Martins_Soares","relpos":2,"ts":1604887342},{"dir":"/home/lucas/Engenharia_de_Computacao/3_periodo/AEDA/2-estruturas_dinamicas/Pratica_3-Etapa_2_-_Lucas_Martins_Soares","file":"src","relpos":1,"ts":1604887342},{"dir":"/home/lucas/Engenharia_de_Computacao/3_periodo/AEDA/2-estruturas_dinamicas","file":"backup","relpos":3,"ts":1604887342},{"dir":"/home/lucas/Engenharia_de_Computacao/3_periodo/AEDA","file":"1-estruturas_estaticas","relpos":2,"ts":1604887342},{"dir":"/home/lucas/Engenharia_de_Computacao/3_periodo/AEDA/1-estruturas_estaticas","file":"..","relpos":0,"ts":1604887342},{"dir":"/home/lucas/Engenharia_de_Computacao/3_periodo/AEDA","file":"2-estruturas_dinamicas","relpos":3,"ts":1604887342},{"dir":"/home/lucas/Engenharia_de_Computacao/3_periodo/AEDA/2-estruturas_dinamicas","file":"ListaPilhaFila","relpos":2,"ts":1604887342},{"dir":"/home/lucas/Engenharia_de_Computacao/3_periodo/AEDA","file":"3-metodos_de_ordenacao","relpos":4,"ts":1604887342},{"dir":"/home/lucas/Engenharia_de_Computacao/3_periodo/AEDA/3-metodos_de_ordenacao","file":"..","relpos":0,"ts":1604887342},{"dir":"/home/lucas/Engenharia_de_Computacao/3_periodo/AEDA","file":"2-estruturas_dinamicas","relpos":3,"ts":1604887342},{"dir":"/home/lucas/Engenharia_de_Computacao/3_periodo/AEDA/2-estruturas_dinamicas","file":"ListaPilhaFila","relpos":2,"ts":1604887342},{"dir":"/home/lucas/Engenharia_de_Computacao/3_periodo/AEDA","file":"0-analise_assintotica","relpos":1,"ts":1604887342},{"dir":"/home/lucas/Engenharia_de_Computacao/3_periodo/AEDA/0-analise_assintotica","file":"TT01","relpos":1,"ts":1604887342},{"dir":"/home/lucas/Engenharia_de_Computacao/3_periodo/AEDA","file":"0-analise_assintotica","relpos":1,"ts":1604887342},{"dir":"/home/lucas/Engenharia_de_Computacao/3_periodo/AEDA/0-analise_assintotica","file":"TT01","relpos":1,"ts":1604887342},{"dir":"/home/lucas/Engenharia_de_Computacao/3_periodo/AEDA","file":"teams","relpos":7,"ts":1604887342},{"dir":"/home/lucas/Engenharia_de_Computacao/3_periodo/AEDA/teams","file":"..","relpos":0,"ts":1604887342},{"dir":"/home/lucas/Engenharia_de_Computacao/3_periodo/AEDA","file":"3-metodos_de_ordenacao","relpos":4,"ts":1604887342},{"dir":"/home/lucas/Engenharia_de_Computacao/3_periodo/AEDA/3-metodos_de_ordenacao","file":"..","relpos":0,"ts":1604887342},{"dir":"/home/lucas/Engenharia_de_Computacao/3_periodo/AEDA","file":"2-estruturas_dinamicas","relpos":3,"ts":1604887342},{"dir":"/home/lucas/Engenharia_de_Computacao/3_periodo/AEDA/2-estruturas_dinamicas","file":"Etapa_2","relpos":1,"ts":1604887342},{"dir":"/home/lucas/Engenharia_de_Computacao/3_periodo/AEDA/2-estruturas_dinamicas/Etapa_2","file":"src","relpos":1,"ts":1604887342},{"dir":"/home/lucas/Engenharia_de_Computacao/3_periodo/AEDA/2-estruturas_dinamicas/Etapa_2/src","file":"main.cpp","relpos":13,"ts":1604887342},{"dir":"/home/lucas","file":"Videos","relpos":6,"ts":1604928436},{"dir":"/home/lucas/Videos","file":"simplescreenrecorder-2020-11-09_08.39.05.mp4","relpos":3,"ts":1604928436},{"dir":"/home/lucas/Downloads","file":"vgeral.pdf","relpos":23,"ts":1604928436},{"dir":"/home/lucas","file":"Videos","relpos":6,"ts":1604928436},{"dir":"/home/lucas/Videos","file":"simplescreenrecorder-2020-11-09_08.39.05.mp4","relpos":3,"ts":1604928436},{"dir":"/home/lucas/Downloads","file":"vgeral.pdf","relpos":23,"ts":1604928436},{"dir":"/home/lucas","file":"Videos","relpos":6,"ts":1604928436},{"dir":"/home/lucas/Videos","file":"simplescreenrecorder-2020-11-09_08.39.05.mp4","relpos":3,"ts":1604928436},{"dir":"/home/lucas/Downloads","file":"vgeral.pdf","relpos":23,"ts":1604928436},{"dir":"/home/lucas","file":"Videos","relpos":6,"ts":1604928436},{"dir":"/home/lucas/Videos","file":"simplescreenrecorder-2020-11-09_08.39.05.mp4","relpos":3,"ts":1604928436},{"dir":"/home/lucas/Downloads","file":"vgeral.pdf","relpos":23,"ts":1604928436},{"dir":"/home/lucas","file":"ffmpeg","relpos":8,"ts":1604928436},{"dir":"/home/lucas/ffmpeg","file":"ffprobe_g","relpos":37,"ts":1604956723},{"dir":"/home/lucas","file":"scripts","relpos":9,"ts":1604956723},{"dir":"/home/lucas/scripts","file":"dsc","relpos":6,"ts":1604956723},{"dir":"/home/lucas/ffmpeg","file":"ffprobe_g","relpos":37,"ts":1604956723},{"dir":"/home/lucas","file":"scripts","relpos":9,"ts":1604956723},{"dir":"/home/lucas/scripts","file":"fsr","relpos":8,"ts":1604956723},{"dir":"/home/lucas/ffmpeg","file":"ffprobe_g","relpos":37,"ts":1604956723},{"dir":"/home/lucas","file":"scripts","relpos":9,"ts":1604956723},{"dir":"/home/lucas/scripts","file":"dsc","relpos":6,"ts":1604956723},{"dir":"/home/lucas/ffmpeg","file":"ffprobe_g","relpos":37,"ts":1604956723},{"dir":"/home/lucas","file":"scripts","relpos":9,"ts":1604956723},{"dir":"/home/lucas/scripts","file":"fsr","relpos":8,"ts":1604956723},{"dir":"/home/lucas/Engenharia_de_Computacao/3_periodo","file":"Horario-Computa√ß√£o-2020-1-ERE.pdf","relpos":9,"ts":1604972867},{"dir":"/home/lucas/Engenharia_de_Computacao/3_periodo/AEDA","file":"teams","relpos":7,"ts":1605042576},{"dir":"/home/lucas/Engenharia_de_Computacao/3_periodo/AEDA/teams","file":"2020-11-05____caiu.mp4","relpos":17,"ts":1605042576},{"dir":"/home/lucas/Engenharia_de_Computacao/3_periodo","file":"AOCO","relpos":2,"ts":1605042576},{"dir":"/home/lucas/Engenharia_de_Computacao/3_periodo/AOCO","file":"Teams","relpos":3,"ts":1605042576},{"dir":"/home/lucas/Engenharia_de_Computacao/3_periodo/AOCO/Teams","file":"2020-11-03.mp4","relpos":19,"ts":1605042576},{"dir":"/home/lucas/Engenharia_de_Computacao/3_periodo","file":"AOCO","relpos":2,"ts":1605042576},{"dir":"/home/lucas/Engenharia_de_Computacao/3_periodo/AOCO","file":"Teams","relpos":3,"ts":1605042576},{"dir":"/home/lucas/Engenharia_de_Computacao/3_periodo/AOCO/Teams","file":"2020-11-03_teorica.mp4","relpos":20,"ts":1605042576},{"dir":"/home/lucas/Engenharia_de_Computacao/3_periodo","file":"AEDA","relpos":1,"ts":1605042576},{"dir":"/home/lucas/Engenharia_de_Computacao/3_periodo/AEDA","file":"teams","relpos":7,"ts":1605042576},{"dir":"/home/lucas/Engenharia_de_Computacao/3_periodo/AEDA/teams","file":"merge.mp4","relpos":18,"ts":1605042576},{"dir":"/home/lucas/Engenharia_de_Computacao/3_periodo","file":"AOCO","relpos":2,"ts":1605094557},{"dir":"/home/lucas/Engenharia_de_Computacao/3_periodo/AOCO","file":"Teams","relpos":3,"ts":1605094557},{"dir":"/home/lucas/Engenharia_de_Computacao/3_periodo/AOCO/Teams","file":"..","relpos":0,"ts":1605094557}],"filters":{"invert":true,"dot":true,"manual":"","auto":""},"last-location":"/home/lucas/Engenharia_de_Computacao/3_periodo/AOCO/Teams","sorting":[2],"preview":false}]}],"active-pane":0,"preview":false,"splitter":{"pos":-1,"ratio":0.5,"orientation":"v","expanded":false}}],"trash":[{"trashed":"/home/lucas/.local/share/vifm/Trash/000_#orgmode.org#","original":"/home/lucas/#orgmode.org#"},{"trashed":"/home/lucas/.local/share/vifm/Trash/000_dmenu_run","original":"/home/lucas/.cache/dmenu_run"},{"trashed":"/home/lucas/.local/share/vifm/Trash/001_dmenu_run","original":"/home/lucas/.cache/dmenu_run"},{"trashed":"/home/lucas/.local/share/vifm/Trash/000_fontconfig","original":"/home/lucas/.config/fontconfig"},{"trashed":"/home/lucas/.local/share/vifm/Trash/000_vifminfo","original":"/home/lucas/.config/vifm/vifminfo"},{"trashed":"/home/lucas/.local/share/vifm/Trash/000_vifminfo.json","original":"/home/lucas/.config/vifm/vifminfo.json"},{"trashed":"/home/lucas/.local/share/vifm/Trash/000_vifminfo.json_2210","original":"/home/lucas/.config/vifm/vifminfo.json_2210"},{"trashed":"/home/lucas/.local/share/vifm/Trash/000_vifminfo.json_547","original":"/home/lucas/.config/vifm/vifminfo.json_547"},{"trashed":"/home/lucas/.local/share/vifm/Trash/000_vifminfo.json_552","original":"/home/lucas/.config/vifm/vifminfo.json_552"},{"trashed":"/home/lucas/.local/share/vifm/Trash/000_vifminfo.json_557","original":"/home/lucas/.config/vifm/vifminfo.json_557"},{"trashed":"/home/lucas/.local/share/vifm/Trash/000_vifminfo.json_560","original":"/home/lucas/.config/vifm/vifminfo.json_560"},{"trashed":"/home/lucas/.local/share/vifm/Trash/000_.inputrc","original":"/home/lucas/.inputrc"},{"trashed":"/home/lucas/.local/share/vifm/Trash/000_after","original":"/home/lucas/.vim/after"},{"trashed":"/home/lucas/.local/share/vifm/Trash/000_2020-10-28 21-53-46.mp4","original":"/home/lucas/2020-10-28 21-53-46.mp4"},{"trashed":"/home/lucas/.local/share/vifm/Trash/000_2020-10-28 21-54-52.mp4","original":"/home/lucas/2020-10-28 21-54-52.mp4"},{"trashed":"/home/lucas/.local/share/vifm/Trash/000_2020-10-28 21-55-12.mp4","original":"/home/lucas/2020-10-28 21-55-12.mp4"},{"trashed":"/home/lucas/.local/share/vifm/Trash/000_2020-10-28 21-55-51.mp4","original":"/home/lucas/2020-10-28 21-55-51.mp4"},{"trashed":"/home/lucas/.local/share/vifm/Trash/000_2020-10-28 21-59-27.mp4","original":"/home/lucas/2020-10-28 21-59-27.mp4"},{"trashed":"/home/lucas/.local/share/vifm/Trash/000_2020-10-28 22-00-49.mp4","original":"/home/lucas/2020-10-28 22-00-49.mp4"},{"trashed":"/home/lucas/.local/share/vifm/Trash/000_2020-10-28 22-01-11.mp4","original":"/home/lucas/2020-10-28 22-01-11.mp4"},{"trashed":"/home/lucas/.local/share/vifm/Trash/000_2020-11-10 12-36-13.mp4","original":"/home/lucas/2020-11-10 12-36-13.mp4"},{"trashed":"/home/lucas/.local/share/vifm/Trash/000_2020-11-11 07-45-46.mp4","original":"/home/lucas/2020-11-11 07-45-46.mp4"},{"trashed":"/home/lucas/.local/share/vifm/Trash/000_Lista.h","original":"/home/lucas/Desktop/Lista.h"},{"trashed":"/home/lucas/.local/share/vifm/Trash/000_Screen Capture_20201110151132.png","original":"/home/lucas/Desktop/Screen Capture_20201110151132.png"},{"trashed":"/home/lucas/.local/share/vifm/Trash/000_TestaLista.h","original":"/home/lucas/Desktop/TestaLista.h"},{"trashed":"/home/lucas/.local/share/vifm/Trash/002_a.out","original":"/home/lucas/Desktop/a.out"},{"trashed":"/home/lucas/.local/share/vifm/Trash/000_.netrwhist","original":"/home/lucas/Desktop/dotfiles/.config/nvim/.netrwhist"},{"trashed":"/home/lucas/.local/share/vifm/Trash/000_init.vim.old","original":"/home/lucas/Desktop/dotfiles/.config/nvim/init.vim.old"},{"trashed":"/home/lucas/.local/share/vifm/Trash/000_init.vim.theprimeage","original":"/home/lucas/Desktop/dotfiles/.config/nvim/init.vim.theprimeage"},{"trashed":"/home/lucas/.local/share/vifm/Trash/000_vifminfo","original":"/home/lucas/Desktop/dotfiles/.config/vifm/vifminfo"},{"trashed":"/home/lucas/.local/share/vifm/Trash/000_vifminfo.json","original":"/home/lucas/Desktop/dotfiles/.config/vifm/vifminfo.json"},{"trashed":"/home/lucas/.local/share/vifm/Trash/000_vifminfo.json_2210","original":"/home/lucas/Desktop/dotfiles/.config/vifm/vifminfo.json_2210"},{"trashed":"/home/lucas/.local/share/vifm/Trash/000_vifminfo.json_534","original":"/home/lucas/Desktop/dotfiles/.config/vifm/vifminfo.json_534"},{"trashed":"/home/lucas/.local/share/vifm/Trash/000_vifminfo.json_547","original":"/home/lucas/Desktop/dotfiles/.config/vifm/vifminfo.json_547"},{"trashed":"/home/lucas/.local/share/vifm/Trash/000_vifminfo.json_552","original":"/home/lucas/Desktop/dotfiles/.config/vifm/vifminfo.json_552"},{"trashed":"/home/lucas/.local/share/vifm/Trash/000_vifminfo.json_557","original":"/home/lucas/Desktop/dotfiles/.config/vifm/vifminfo.json_557"},{"trashed":"/home/lucas/.local/share/vifm/Trash/000_vifminfo.json_560","original":"/home/lucas/Desktop/dotfiles/.config/vifm/vifminfo.json_560"},{"trashed":"/home/lucas/.local/share/vifm/Trash/000_.git","original":"/home/lucas/Desktop/dotfiles/.config/zathura/.git"},{"trashed":"/home/lucas/.local/share/vifm/Trash/000_.github","original":"/home/lucas/Desktop/dotfiles/.config/zathura/.github"},{"trashed":"/home/lucas/.local/share/vifm/Trash/000_INSTALL.md","original":"/home/lucas/Desktop/dotfiles/.config/zathura/INSTALL.md"},{"trashed":"/home/lucas/.local/share/vifm/Trash/000_LICENSE","original":"/home/lucas/Desktop/dotfiles/.config/zathura/LICENSE"},{"trashed":"/home/lucas/.local/share/vifm/Trash/000_README.md","original":"/home/lucas/Desktop/dotfiles/.config/zathura/README.md"},{"trashed":"/home/lucas/.local/share/vifm/Trash/000_lightmode.png","original":"/home/lucas/Desktop/dotfiles/.config/zathura/lightmode.png"},{"trashed":"/home/lucas/.local/share/vifm/Trash/000_screenshot.png","original":"/home/lucas/Desktop/dotfiles/.config/zathura/screenshot.png"},{"trashed":"/home/lucas/.local/share/vifm/Trash/000_netrw.vim","original":"/home/lucas/Desktop/dotfiles/home-user-.vim-after-ftplugin/netrw.vim"},{"trashed":"/home/lucas/.local/share/vifm/Trash/000_scripts.txt","original":"/home/lucas/Desktop/dotfiles/scripts/scripts.txt"},{"trashed":"/home/lucas/.local/share/vifm/Trash/000_dracula.js","original":"/home/lucas/Desktop/dracula.js"},{"trashed":"/home/lucas/.local/share/vifm/Trash/000_teste.cpp","original":"/home/lucas/Desktop/teste.cpp"},{"trashed":"/home/lucas/.local/share/vifm/Trash/000_3.1a3.2-lista-arranjo.c","original":"/home/lucas/Downloads/3.1a3.2-lista-arranjo.c"},{"trashed":"/home/lucas/.local/share/vifm/Trash/000_Algoritmo_Recomenda√ß√£o_Patrick","original":"/home/lucas/Downloads/Algoritmo_Recomenda√ß√£o_Patrick"},{"trashed":"/home/lucas/.local/share/vifm/Trash/001_Algoritmo_Recomenda√ß√£o_Patrick","original":"/home/lucas/Downloads/Algoritmo_Recomenda√ß√£o_Patrick"},{"trashed":"/home/lucas/.local/share/vifm/Trash/000_Algoritmo_Recomenda√ß√£o_Patrick.zip","original":"/home/lucas/Downloads/Algoritmo_Recomenda√ß√£o_Patrick.zip"},{"trashed":"/home/lucas/.local/share/vifm/Trash/001_Algoritmo_Recomenda√ß√£o_Patrick.zip","original":"/home/lucas/Downloads/Algoritmo_Recomenda√ß√£o_Patrick.zip"},{"trashed":"/home/lucas/.local/share/vifm/Trash/011_main","original":"/home/lucas/Downloads/Algoritmo_Recomenda√ß√£o_Patrick/main"},{"trashed":"/home/lucas/.local/share/vifm/Trash/000_run","original":"/home/lucas/Downloads/Algoritmo_Recomenda√ß√£o_Patrick/run"},{"trashed":"/home/lucas/.local/share/vifm/Trash/001_run","original":"/home/lucas/Downloads/Algoritmo_Recomenda√ß√£o_Patrick/run"},{"trashed":"/home/lucas/.local/share/vifm/Trash/000_Como +Æ a sua internet?.csv","original":"/home/lucas/Downloads/Como +Æ a sua internet?.csv"},{"trashed":"/home/lucas/.local/share/vifm/Trash/000_Como √© a sua internet .csv.zip","original":"/home/lucas/Downloads/Como √© a sua internet .csv.zip"},{"trashed":"/home/lucas/.local/share/vifm/Trash/000_ListaEstatica","original":"/home/lucas/Downloads/ListaEstatica"},{"trashed":"/home/lucas/.local/share/vifm/Trash/000_ListaEstatica.c","original":"/home/lucas/Downloads/ListaEstatica.c"},{"trashed":"/home/lucas/.local/share/vifm/Trash/000_Lucas.zip","original":"/home/lucas/Downloads/Lucas.zip"},{"trashed":"/home/lucas/.local/share/vifm/Trash/000_WhatsApp Image 2020-11-05 at 16.23.35.jpeg","original":"/home/lucas/Downloads/WhatsApp Image 2020-11-05 at 16.23.35.jpeg"},{"trashed":"/home/lucas/.local/share/vifm/Trash/000_WhatsApp Image 2020-11-05 at 21.43.24(1).jpeg","original":"/home/lucas/Downloads/WhatsApp Image 2020-11-05 at 21.43.24(1).jpeg"},{"trashed":"/home/lucas/.local/share/vifm/Trash/001_WhatsApp Image 2020-11-05 at 21.43.24(1).jpeg","original":"/home/lucas/Downloads/WhatsApp Image 2020-11-05 at 21.43.24(1).jpeg"},{"trashed":"/home/lucas/.local/share/vifm/Trash/000_WhatsApp Image 2020-11-05 at 21.43.24.jpeg","original":"/home/lucas/Downloads/WhatsApp Image 2020-11-05 at 21.43.24.jpeg"},{"trashed":"/home/lucas/.local/share/vifm/Trash/000_clang-format.py","original":"/home/lucas/Downloads/clang-format.py"},{"trashed":"/home/lucas/.local/share/vifm/Trash/000_prog3.11","original":"/home/lucas/Downloads/prog3.11"},{"trashed":"/home/lucas/.local/share/vifm/Trash/000_prog3.11-fila-auto-referencias.zip","original":"/home/lucas/Downloads/prog3.11-fila-auto-referencias.zip"},{"trashed":"/home/lucas/.local/share/vifm/Trash/000_prog3.2","original":"/home/lucas/Downloads/prog3.2"},{"trashed":"/home/lucas/.local/share/vifm/Trash/000_prog3.2-lista-auto-referencias.zip","original":"/home/lucas/Downloads/prog3.2-lista-auto-referencias.zip"},{"trashed":"/home/lucas/.local/share/vifm/Trash/000_prog4.3-16-ordenacao(1).zip","original":"/home/lucas/Downloads/prog4.3-16-ordenacao(1).zip"},{"trashed":"/home/lucas/.local/share/vifm/Trash/000_prog4.3-16-ordenacao(2).zip","original":"/home/lucas/Downloads/prog4.3-16-ordenacao(2).zip"},{"trashed":"/home/lucas/.local/share/vifm/Trash/000_questoes.txt","original":"/home/lucas/Downloads/questoes.txt"},{"trashed":"/home/lucas/.local/share/vifm/Trash/000_simplescreenrecorder-2020-10-28.mp4","original":"/home/lucas/Downloads/simplescreenrecorder-2020-10-28.mp4"},{"trashed":"/home/lucas/.local/share/vifm/Trash/000_users(1).zip","original":"/home/lucas/Downloads/users(1).zip"},{"trashed":"/home/lucas/.local/share/vifm/Trash/001_users(1).zip","original":"/home/lucas/Downloads/users(1).zip"},{"trashed":"/home/lucas/.local/share/vifm/Trash/002_users.zip","original":"/home/lucas/Downloads/users.zip"},{"trashed":"/home/lucas/.local/share/vifm/Trash/003_users.zip","original":"/home/lucas/Downloads/users.zip"},{"trashed":"/home/lucas/.local/share/vifm/Trash/004_users.zip","original":"/home/lucas/Downloads/users.zip"},{"trashed":"/home/lucas/.local/share/vifm/Trash/000_Main.out","original":"/home/lucas/Engenharia_de_Computacao/2_periodo/Laborat√≥rio de Programa√ß√£o/exercicios/aula3/exercicio5/Main.out"},{"trashed":"/home/lucas/.local/share/vifm/Trash/000_a.out","original":"/home/lucas/Engenharia_de_Computacao/2_periodo/Laborat√≥rio de Programa√ß√£o/exercicios/aula3/exercicio5/a.out"},{"trashed":"/home/lucas/.local/share/vifm/Trash/004_main","original":"/home/lucas/Engenharia_de_Computacao/2_periodo/Laborat√≥rio de Programa√ß√£o/exercicios/aula3/exercicio5/main"},{"trashed":"/home/lucas/.local/share/vifm/Trash/000_novo.txt","original":"/home/lucas/Engenharia_de_Computacao/2_periodo/Laborat√≥rio de Programa√ß√£o/exercicios/aula3/exercicio5/novo.txt"},{"trashed":"/home/lucas/.local/share/vifm/Trash/000_FPHeapMax.hpp","original":"/home/lucas/Engenharia_de_Computacao/3_periodo/AEDA/2-estruturas_dinamicas/Pratica_3-Etapa_2_-_Lucas_Martins_Soares/src/FPHeapMax.hpp"},{"trashed":"/home/lucas/.local/share/vifm/Trash/000_Ordenacao.hpp","original":"/home/lucas/Engenharia_de_Computacao/3_periodo/AEDA/2-estruturas_dinamicas/Pratica_3-Etapa_2_-_Lucas_Martins_Soares/src/Ordenacao.hpp"},{"trashed":"/home/lucas/.local/share/vifm/Trash/012_main","original":"/home/lucas/Engenharia_de_Computacao/3_periodo/AEDA/2-estruturas_dinamicas/Pratica_3-Etapa_2_-_Lucas_Martins_Soares/src/main"},{"trashed":"/home/lucas/.local/share/vifm/Trash/013_main","original":"/home/lucas/Engenharia_de_Computacao/3_periodo/AEDA/2-estruturas_dinamicas/Pratica_3-Etapa_2_-_Lucas_Martins_Soares/src/main"},{"trashed":"/home/lucas/.local/share/vifm/Trash/014_main","original":"/home/lucas/Engenharia_de_Computacao/3_periodo/AEDA/2-estruturas_dinamicas/Pratica_3-Etapa_2_-_Lucas_Martins_Soares/src/main"},{"trashed":"/home/lucas/.local/share/vifm/Trash/000_1-lista_arranjo","original":"/home/lucas/Engenharia_de_Computacao/3_periodo/AEDA/aula2-0_est√°tica/ListaPilhaFila/C/estatica/1-lista_arranjo"},{"trashed":"/home/lucas/.local/share/vifm/Trash/000_backup","original":"/home/lucas/Engenharia_de_Computacao/3_periodo/AEDA/aula2-0_est√°tica/backup"},{"trashed":"/home/lucas/.local/share/vifm/Trash/001_backup","original":"/home/lucas/Engenharia_de_Computacao/3_periodo/AEDA/aula2-0_est√°tica/backup"},{"trashed":"/home/lucas/.local/share/vifm/Trash/002_TAGS","original":"/home/lucas/Engenharia_de_Computacao/3_periodo/AEDA/aula2-0_est√°tica/pratica3/Pratica_3-Etapa_1_-_Lucas_Martins_Soares/TAGS"},{"trashed":"/home/lucas/.local/share/vifm/Trash/008_main","original":"/home/lucas/Engenharia_de_Computacao/3_periodo/AEDA/aula2-0_est√°tica/pratica3/Pratica_3-Etapa_1_-_Lucas_Martins_Soares/main"},{"trashed":"/home/lucas/.local/share/vifm/Trash/000_gtoken.cpp","original":"/home/lucas/Engenharia_de_Computacao/3_periodo/AEDA/aula2-0_est√°tica/pratica3/TokenizacÃßaÃÉo + Template2/gtoken.cpp"},{"trashed":"/home/lucas/.local/share/vifm/Trash/000_README","original":"/home/lucas/Engenharia_de_Computacao/3_periodo/AEDA/aula2-0_est√°tica/pratica3/teste/README"},{"trashed":"/home/lucas/.local/share/vifm/Trash/001_a.out","original":"/home/lucas/Engenharia_de_Computacao/3_periodo/AEDA/aula2-0_est√°tica/pratica3/teste/a.out"},{"trashed":"/home/lucas/.local/share/vifm/Trash/000_1000.csv","original":"/home/lucas/Engenharia_de_Computacao/3_periodo/AEDA/aula2-1_dinamica/Pratica_3-Etapa_2_-_Lucas_Martins_Soares/1000.csv"},{"trashed":"/home/lucas/.local/share/vifm/Trash/000_TAGS","original":"/home/lucas/Engenharia_de_Computacao/3_periodo/AEDA/aula2-1_dinamica/Pratica_3-Etapa_2_-_Lucas_Martins_Soares/TAGS"},{"trashed":"/home/lucas/.local/share/vifm/Trash/000_etapa1_resolucao","original":"/home/lucas/Engenharia_de_Computacao/3_periodo/AEDA/aula2-1_dinamica/Pratica_3-Etapa_2_-_Lucas_Martins_Soares/etapa1_resolucao"},{"trashed":"/home/lucas/.local/share/vifm/Trash/000_etapa1_resolucao.c","original":"/home/lucas/Engenharia_de_Computacao/3_periodo/AEDA/aula2-1_dinamica/Pratica_3-Etapa_2_-_Lucas_Martins_Soares/etapa1_resolucao.c"},{"trashed":"/home/lucas/.local/share/vifm/Trash/000_main","original":"/home/lucas/Engenharia_de_Computacao/3_periodo/AEDA/aula2-1_dinamica/Pratica_3-Etapa_2_-_Lucas_Martins_Soares/main"},{"trashed":"/home/lucas/.local/share/vifm/Trash/005_main","original":"/home/lucas/Engenharia_de_Computacao/3_periodo/AEDA/aula2-1_dinamica/Pratica_3-Etapa_2_-_Lucas_Martins_Soares/main"},{"trashed":"/home/lucas/.local/share/vifm/Trash/000_matriz_de_fatoracao.txt","original":"/home/lucas/Engenharia_de_Computacao/3_periodo/AEDA/aula2-1_dinamica/Pratica_3-Etapa_2_-_Lucas_Martins_Soares/matriz_de_fatoracao.txt"},{"trashed":"/home/lucas/.local/share/vifm/Trash/000_pequeno.txt","original":"/home/lucas/Engenharia_de_Computacao/3_periodo/AEDA/aula2-1_dinamica/Pratica_3-Etapa_2_-_Lucas_Martins_Soares/pequeno.txt"},{"trashed":"/home/lucas/.local/share/vifm/Trash/001_pequeno.txt","original":"/home/lucas/Engenharia_de_Computacao/3_periodo/AEDA/aula2-1_dinamica/Pratica_3-Etapa_2_-_Lucas_Martins_Soares/pequeno.txt"},{"trashed":"/home/lucas/.local/share/vifm/Trash/000_Fila(1).cpp","original":"/home/lucas/Engenharia_de_Computacao/3_periodo/AEDA/aula2-1_dinamica/Pratica_3-Etapa_2_-_Lucas_Martins_Soares/src/Fila(1).cpp"},{"trashed":"/home/lucas/.local/share/vifm/Trash/001_Fila.cpp","original":"/home/lucas/Engenharia_de_Computacao/3_periodo/AEDA/aula2-1_dinamica/Pratica_3-Etapa_2_-_Lucas_Martins_Soares/src/Fila.cpp"},{"trashed":"/home/lucas/.local/share/vifm/Trash/001_Fila.hpp","original":"/home/lucas/Engenharia_de_Computacao/3_periodo/AEDA/aula2-1_dinamica/Pratica_3-Etapa_2_-_Lucas_Martins_Soares/src/Fila.hpp"},{"trashed":"/home/lucas/.local/share/vifm/Trash/001_MatrizDeFatoracao.cpp","original":"/home/lucas/Engenharia_de_Computacao/3_periodo/AEDA/aula2-1_dinamica/Pratica_3-Etapa_2_-_Lucas_Martins_Soares/src/MatrizDeFatoracao.cpp"},{"trashed":"/home/lucas/.local/share/vifm/Trash/003_MatrizDeFatoracao.cpp","original":"/home/lucas/Engenharia_de_Computacao/3_periodo/AEDA/aula2-1_dinamica/Pratica_3-Etapa_2_-_Lucas_Martins_Soares/src/MatrizDeFatoracao.cpp"},{"trashed":"/home/lucas/.local/share/vifm/Trash/001_MatrizDeFatoracao.hpp","original":"/home/lucas/Engenharia_de_Computacao/3_periodo/AEDA/aula2-1_dinamica/Pratica_3-Etapa_2_-_Lucas_Martins_Soares/src/MatrizDeFatoracao.hpp"},{"trashed":"/home/lucas/.local/share/vifm/Trash/003_MatrizDeFatoracao.hpp","original":"/home/lucas/Engenharia_de_Computacao/3_periodo/AEDA/aula2-1_dinamica/Pratica_3-Etapa_2_-_Lucas_Martins_Soares/src/MatrizDeFatoracao.hpp"},{"trashed":"/home/lucas/.local/share/vifm/Trash/001_Pilha.cpp","original":"/home/lucas/Engenharia_de_Computacao/3_periodo/AEDA/aula2-1_dinamica/Pratica_3-Etapa_2_-_Lucas_Martins_Soares/src/Pilha.cpp"},{"trashed":"/home/lucas/.local/share/vifm/Trash/001_Pilha.hpp","original":"/home/lucas/Engenharia_de_Computacao/3_periodo/AEDA/aula2-1_dinamica/Pratica_3-Etapa_2_-_Lucas_Martins_Soares/src/Pilha.hpp"},{"trashed":"/home/lucas/.local/share/vifm/Trash/001_TAGS","original":"/home/lucas/Engenharia_de_Computacao/3_periodo/AEDA/aula2-1_dinamica/Pratica_3-Etapa_2_-_Lucas_Martins_Soares/src/TAGS"},{"trashed":"/home/lucas/.local/share/vifm/Trash/001_Tokenizer.cpp","original":"/home/lucas/Engenharia_de_Computacao/3_periodo/AEDA/aula2-1_dinamica/Pratica_3-Etapa_2_-_Lucas_Martins_Soares/src/Tokenizer.cpp"},{"trashed":"/home/lucas/.local/share/vifm/Trash/002_Tokenizer.cpp","original":"/home/lucas/Engenharia_de_Computacao/3_periodo/AEDA/aula2-1_dinamica/Pratica_3-Etapa_2_-_Lucas_Martins_Soares/src/Tokenizer.cpp"},{"trashed":"/home/lucas/.local/share/vifm/Trash/001_Tokenizer.hpp","original":"/home/lucas/Engenharia_de_Computacao/3_periodo/AEDA/aula2-1_dinamica/Pratica_3-Etapa_2_-_Lucas_Martins_Soares/src/Tokenizer.hpp"},{"trashed":"/home/lucas/.local/share/vifm/Trash/002_Tokenizer.hpp","original":"/home/lucas/Engenharia_de_Computacao/3_periodo/AEDA/aula2-1_dinamica/Pratica_3-Etapa_2_-_Lucas_Martins_Soares/src/Tokenizer.hpp"},{"trashed":"/home/lucas/.local/share/vifm/Trash/000_UsuariosSimilares.cpp","original":"/home/lucas/Engenharia_de_Computacao/3_periodo/AEDA/aula2-1_dinamica/Pratica_3-Etapa_2_-_Lucas_Martins_Soares/src/UsuariosSimilares.cpp"},{"trashed":"/home/lucas/.local/share/vifm/Trash/000_UsuariosSimilares.hpp","original":"/home/lucas/Engenharia_de_Computacao/3_periodo/AEDA/aula2-1_dinamica/Pratica_3-Etapa_2_-_Lucas_Martins_Soares/src/UsuariosSimilares.hpp"},{"trashed":"/home/lucas/.local/share/vifm/Trash/001_main","original":"/home/lucas/Engenharia_de_Computacao/3_periodo/AEDA/aula2-1_dinamica/Pratica_3-Etapa_2_-_Lucas_Martins_Soares/src/main"},{"trashed":"/home/lucas/.local/share/vifm/Trash/002_main","original":"/home/lucas/Engenharia_de_Computacao/3_periodo/AEDA/aula2-1_dinamica/Pratica_3-Etapa_2_-_Lucas_Martins_Soares/src/main"},{"trashed":"/home/lucas/.local/share/vifm/Trash/003_main","original":"/home/lucas/Engenharia_de_Computacao/3_periodo/AEDA/aula2-1_dinamica/Pratica_3-Etapa_2_-_Lucas_Martins_Soares/src/main"},{"trashed":"/home/lucas/.local/share/vifm/Trash/006_main","original":"/home/lucas/Engenharia_de_Computacao/3_periodo/AEDA/aula2-1_dinamica/Pratica_3-Etapa_2_-_Lucas_Martins_Soares/src/main"},{"trashed":"/home/lucas/.local/share/vifm/Trash/009_main","original":"/home/lucas/Engenharia_de_Computacao/3_periodo/AEDA/aula2-1_dinamica/Pratica_3-Etapa_2_-_Lucas_Martins_Soares/src/main"},{"trashed":"/home/lucas/.local/share/vifm/Trash/001_main.cpp","original":"/home/lucas/Engenharia_de_Computacao/3_periodo/AEDA/aula2-1_dinamica/Pratica_3-Etapa_2_-_Lucas_Martins_Soares/src/main.cpp"},{"trashed":"/home/lucas/.local/share/vifm/Trash/003_main.cpp","original":"/home/lucas/Engenharia_de_Computacao/3_periodo/AEDA/aula2-1_dinamica/Pratica_3-Etapa_2_-_Lucas_Martins_Soares/src/main.cpp"},{"trashed":"/home/lucas/.local/share/vifm/Trash/001_matriz_de_fatoracao.txt","original":"/home/lucas/Engenharia_de_Computacao/3_periodo/AEDA/aula2-1_dinamica/Pratica_3-Etapa_2_-_Lucas_Martins_Soares/src/matriz_de_fatoracao.txt"},{"trashed":"/home/lucas/.local/share/vifm/Trash/000___MACOSX","original":"/home/lucas/Engenharia_de_Computacao/3_periodo/AEDA/aula2-1_dinamica/__MACOSX"},{"trashed":"/home/lucas/.local/share/vifm/Trash/001_users.zip","original":"/home/lucas/Engenharia_de_Computacao/3_periodo/AEDA/aula2-1_dinamica/users.zip"},{"trashed":"/home/lucas/.local/share/vifm/Trash/002_2020-11-05.mp4","original":"/home/lucas/Engenharia_de_Computacao/3_periodo/AEDA/teams/2020-11-05.mp4"},{"trashed":"/home/lucas/.local/share/vifm/Trash/000_._Arquitetura_e_Organiza√ß√£o_de_Computadores.pdf","original":"/home/lucas/Engenharia_de_Computacao/3_periodo/AOCO/._Arquitetura_e_Organiza√ß√£o_de_Computadores.pdf"},{"trashed":"/home/lucas/.local/share/vifm/Trash/000_._Arquitetura_e_Organiza√ß√£o_de_Computadores_-_William_Stallings.pdf","original":"/home/lucas/Engenharia_de_Computacao/3_periodo/AOCO/._Arquitetura_e_Organiza√ß√£o_de_Computadores_-_William_Stallings.pdf"},{"trashed":"/home/lucas/.local/share/vifm/Trash/000_.~lock.Arquitetura_e_Organiza√ß√£o_de_Computadores.pdf#","original":"/home/lucas/Engenharia_de_Computacao/3_periodo/AOCO/.~lock.Arquitetura_e_Organiza√ß√£o_de_Computadores.pdf#"},{"trashed":"/home/lucas/.local/share/vifm/Trash/000_Contadores","original":"/home/lucas/Engenharia_de_Computacao/3_periodo/AOCO/Contadores"},{"trashed":"/home/lucas/.local/share/vifm/Trash/000_Data_Path","original":"/home/lucas/Engenharia_de_Computacao/3_periodo/AOCO/Data_Path"},{"trashed":"/home/lucas/.local/share/vifm/Trash/000_Data_Path_-_Lucas_Martins_Soares.zip","original":"/home/lucas/Engenharia_de_Computacao/3_periodo/AOCO/Data_Path_-_Lucas_Martins_Soares.zip"},{"trashed":"/home/lucas/.local/share/vifm/Trash/001_Data_Path_-_Lucas_Martins_Soares.zip","original":"/home/lucas/Engenharia_de_Computacao/3_periodo/AOCO/Data_Path_-_Lucas_Martins_Soares.zip"},{"trashed":"/home/lucas/.local/share/vifm/Trash/000_Trabalho Pr√°tico ‚Äì Assembly do IAS.pdf","original":"/home/lucas/Engenharia_de_Computacao/3_periodo/AOCO/Exercicios/IAS/Trabalho Pr√°tico ‚Äì Assembly do IAS.pdf"},{"trashed":"/home/lucas/.local/share/vifm/Trash/000_example13.pdf","original":"/home/lucas/Engenharia_de_Computacao/3_periodo/AOCO/Exercicios/IAS/example13.pdf"},{"trashed":"/home/lucas/.local/share/vifm/Trash/000_pdf","original":"/home/lucas/Engenharia_de_Computacao/3_periodo/AOCO/Exercicios/IAS/pdf"},{"trashed":"/home/lucas/.local/share/vifm/Trash/000_test.html","original":"/home/lucas/Engenharia_de_Computacao/3_periodo/AOCO/Exercicios/IAS/test.html"},{"trashed":"/home/lucas/.local/share/vifm/Trash/000_test.pdf","original":"/home/lucas/Engenharia_de_Computacao/3_periodo/AOCO/Exercicios/IAS/test.pdf"},{"trashed":"/home/lucas/.local/share/vifm/Trash/000_Interconex√£o","original":"/home/lucas/Engenharia_de_Computacao/3_periodo/AOCO/Exercicios/Interconex√£o"},{"trashed":"/home/lucas/.local/share/vifm/Trash/000_Leitura Complementar.html","original":"/home/lucas/Engenharia_de_Computacao/3_periodo/AOCO/Exercicios/Leitura Complementar.html"},{"trashed":"/home/lucas/.local/share/vifm/Trash/000_Leitura Complementar.pdf","original":"/home/lucas/Engenharia_de_Computacao/3_periodo/AOCO/Exercicios/Leitura Complementar.pdf"},{"trashed":"/home/lucas/.local/share/vifm/Trash/000_barramento","original":"/home/lucas/Engenharia_de_Computacao/3_periodo/AOCO/Exercicios/barramento"},{"trashed":"/home/lucas/.local/share/vifm/Trash/000_de","original":"/home/lucas/Engenharia_de_Computacao/3_periodo/AOCO/Exercicios/de"},{"trashed":"/home/lucas/.local/share/vifm/Trash/000_JuntadoPartes","original":"/home/lucas/Engenharia_de_Computacao/3_periodo/AOCO/JuntadoPartes"},{"trashed":"/home/lucas/.local/share/vifm/Trash/000_LAB-AOCO","original":"/home/lucas/Engenharia_de_Computacao/3_periodo/AOCO/LAB-AOCO"},{"trashed":"/home/lucas/.local/share/vifm/Trash/000_Lista_para_Entrega_-_Memorias","original":"/home/lucas/Engenharia_de_Computacao/3_periodo/AOCO/Lista_para_Entrega_-_Memorias"},{"trashed":"/home/lucas/.local/share/vifm/Trash/000_Memorias","original":"/home/lucas/Engenharia_de_Computacao/3_periodo/AOCO/Memorias"},{"trashed":"/home/lucas/.local/share/vifm/Trash/000_Revisao_de_contador_sincrono","original":"/home/lucas/Engenharia_de_Computacao/3_periodo/AOCO/Revisao_de_contador_sincrono"},{"trashed":"/home/lucas/.local/share/vifm/Trash/000_exercicios","original":"/home/lucas/Engenharia_de_Computacao/3_periodo/AOCO/exercicios"},{"trashed":"/home/lucas/.local/share/vifm/Trash/001_leitura_complementar.txt","original":"/home/lucas/Engenharia_de_Computacao/3_periodo/AOCO/leitura_complementar.txt"},{"trashed":"/home/lucas/.local/share/vifm/Trash/000_mux-demux","original":"/home/lucas/Engenharia_de_Computacao/3_periodo/AOCO/mux-demux"},{"trashed":"/home/lucas/.local/share/vifm/Trash/002_Algoritmo_Recomenda√ß√£o_Patrick.zip","original":"/home/lucas/Engenharia_de_Computacao/3_periodo/Algoritmo_Recomenda√ß√£o_Patrick.zip"},{"trashed":"/home/lucas/.local/share/vifm/Trash/000_simplescreenrecorder-2020-10-28_22.12.02.mp4","original":"/home/lucas/Videos/simplescreenrecorder-2020-10-28_22.12.02.mp4"},{"trashed":"/home/lucas/.local/share/vifm/Trash/000_simplescreenrecorder-2020-10-28_22.21.23.mp4","original":"/home/lucas/Videos/simplescreenrecorder-2020-10-28_22.21.23.mp4"},{"trashed":"/home/lucas/.local/share/vifm/Trash/000_simplescreenrecorder-2020-11-09_08.36.05.mp4","original":"/home/lucas/Videos/simplescreenrecorder-2020-11-09_08.36.05.mp4"},{"trashed":"/home/lucas/.local/share/vifm/Trash/000_simplescreenrecorder-2020-11-09_08.39.05.mp4","original":"/home/lucas/Videos/simplescreenrecorder-2020-11-09_08.39.05.mp4"},{"trashed":"/home/lucas/.local/share/vifm/Trash/000_simplescreenrecorder-2020-11-10_13.21.29.mp4","original":"/home/lucas/Videos/simplescreenrecorder-2020-11-10_13.21.29.mp4"},{"trashed":"/home/lucas/.local/share/vifm/Trash/000_simplescreenrecorder-2020-11-10_13.22.54.mp4","original":"/home/lucas/Videos/simplescreenrecorder-2020-11-10_13.22.54.mp4"},{"trashed":"/home/lucas/.local/share/vifm/Trash/000_simplescreenrecorder-2020-11-11_07.36.17.mp4","original":"/home/lucas/Videos/simplescreenrecorder-2020-11-11_07.36.17.mp4"},{"trashed":"/home/lucas/.local/share/vifm/Trash/000_simplescreenrecorder-2020-11-11_07.39.43.h264","original":"/home/lucas/Videos/simplescreenrecorder-2020-11-11_07.39.43.h264"},{"trashed":"/home/lucas/.local/share/vifm/Trash/000_simplescreenrecorder-2020-11-11_07.39.50.h264","original":"/home/lucas/Videos/simplescreenrecorder-2020-11-11_07.39.50.h264"},{"trashed":"/home/lucas/.local/share/vifm/Trash/000_simplescreenrecorder-2020-11-11_07.40.23.h264","original":"/home/lucas/Videos/simplescreenrecorder-2020-11-11_07.40.23.h264"},{"trashed":"/home/lucas/.local/share/vifm/Trash/000_simplescreenrecorder-2020-11-11_07.40.31.h264","original":"/home/lucas/Videos/simplescreenrecorder-2020-11-11_07.40.31.h264"},{"trashed":"/home/lucas/.local/share/vifm/Trash/000_simplescreenrecorder.mp4","original":"/home/lucas/Videos/simplescreenrecorder.mp4"},{"trashed":"/home/lucas/.local/share/vifm/Trash/000_alsa.mkv","original":"/home/lucas/alsa.mkv"},{"trashed":"/home/lucas/.local/share/vifm/Trash/000_ffmpeg","original":"/home/lucas/ffmpeg"},{"trashed":"/home/lucas/.local/share/vifm/Trash/006_output.mkv","original":"/home/lucas/ffmpeg/output.mkv"},{"trashed":"/home/lucas/.local/share/vifm/Trash/000_fonts.txt","original":"/home/lucas/fonts.txt"},{"trashed":"/home/lucas/.local/share/vifm/Trash/000_kazam","original":"/home/lucas/kazam"},{"trashed":"/home/lucas/.local/share/vifm/Trash/000_lossless.mkv","original":"/home/lucas/lossless.mkv"},{"trashed":"/home/lucas/.local/share/vifm/Trash/001_lossless.mkv","original":"/home/lucas/lossless.mkv"},{"trashed":"/home/lucas/.local/share/vifm/Trash/002_lossless.mkv","original":"/home/lucas/lossless.mkv"},{"trashed":"/home/lucas/.local/share/vifm/Trash/000_lossless.mp4","original":"/home/lucas/lossless.mp4"},{"trashed":"/home/lucas/.local/share/vifm/Trash/010_main","original":"/home/lucas/main"},{"trashed":"/home/lucas/.local/share/vifm/Trash/000_mozilla.pdf","original":"/home/lucas/mozilla.pdf"},{"trashed":"/home/lucas/.local/share/vifm/Trash/000_out.mp4","original":"/home/lucas/out.mp4"},{"trashed":"/home/lucas/.local/share/vifm/Trash/000_outfile.mkv","original":"/home/lucas/outfile.mkv"},{"trashed":"/home/lucas/.local/share/vifm/Trash/001_outfile.mkv","original":"/home/lucas/outfile.mkv"},{"trashed":"/home/lucas/.local/share/vifm/Trash/000_output.mkv","original":"/home/lucas/output.mkv"},{"trashed":"/home/lucas/.local/share/vifm/Trash/001_output.mkv","original":"/home/lucas/output.mkv"},{"trashed":"/home/lucas/.local/share/vifm/Trash/002_output.mkv","original":"/home/lucas/output.mkv"},{"trashed":"/home/lucas/.local/share/vifm/Trash/003_output.mkv","original":"/home/lucas/output.mkv"},{"trashed":"/home/lucas/.local/share/vifm/Trash/004_output.mkv","original":"/home/lucas/output.mkv"},{"trashed":"/home/lucas/.local/share/vifm/Trash/005_output.mkv","original":"/home/lucas/output.mkv"},{"trashed":"/home/lucas/.local/share/vifm/Trash/007_output.mkv","original":"/home/lucas/output.mkv"},{"trashed":"/home/lucas/.local/share/vifm/Trash/008_output.mkv","original":"/home/lucas/output.mkv"},{"trashed":"/home/lucas/.local/share/vifm/Trash/009_output.mkv","original":"/home/lucas/output.mkv"},{"trashed":"/home/lucas/.local/share/vifm/Trash/010_output.mkv","original":"/home/lucas/output.mkv"},{"trashed":"/home/lucas/.local/share/vifm/Trash/013_output.mkv","original":"/home/lucas/output.mkv"},{"trashed":"/home/lucas/.local/share/vifm/Trash/014_output.mkv","original":"/home/lucas/output.mkv"},{"trashed":"/home/lucas/.local/share/vifm/Trash/000_output.mp4","original":"/home/lucas/output.mp4"},{"trashed":"/home/lucas/.local/share/vifm/Trash/001_output.mp4","original":"/home/lucas/output.mp4"},{"trashed":"/home/lucas/.local/share/vifm/Trash/002_output.mp4","original":"/home/lucas/output.mp4"},{"trashed":"/home/lucas/.local/share/vifm/Trash/003_output.mp4","original":"/home/lucas/output.mp4"},{"trashed":"/home/lucas/.local/share/vifm/Trash/004_output.mp4","original":"/home/lucas/output.mp4"},{"trashed":"/home/lucas/.local/share/vifm/Trash/005_output.mp4","original":"/home/lucas/output.mp4"},{"trashed":"/home/lucas/.local/share/vifm/Trash/006_output.mp4","original":"/home/lucas/output.mp4"},{"trashed":"/home/lucas/.local/share/vifm/Trash/007_output.mp4","original":"/home/lucas/output.mp4"},{"trashed":"/home/lucas/.local/share/vifm/Trash/009_output.mp4","original":"/home/lucas/output.mp4"},{"trashed":"/home/lucas/.local/share/vifm/Trash/010_output.mp4","original":"/home/lucas/output.mp4"},{"trashed":"/home/lucas/.local/share/vifm/Trash/011_output.mp4","original":"/home/lucas/output.mp4"},{"trashed":"/home/lucas/.local/share/vifm/Trash/012_output.mp4","original":"/home/lucas/output.mp4"},{"trashed":"/home/lucas/.local/share/vifm/Trash/000_print-events.txt","original":"/home/lucas/print-events.txt"},{"trashed":"/home/lucas/.local/share/vifm/Trash/000_pulse.mkv","original":"/home/lucas/pulse.mkv"},{"trashed":"/home/lucas/.local/share/vifm/Trash/001_pulse.mkv","original":"/home/lucas/pulse.mkv"},{"trashed":"/home/lucas/.local/share/vifm/Trash/000_pulse.mp4","original":"/home/lucas/pulse.mp4"},{"trashed":"/home/lucas/.local/share/vifm/Trash/001_pulse.mp4","original":"/home/lucas/pulse.mp4"},{"trashed":"/home/lucas/.local/share/vifm/Trash/002_pulse.mp4","original":"/home/lucas/pulse.mp4"},{"trashed":"/home/lucas/.local/share/vifm/Trash/003_pulse.mp4","original":"/home/lucas/pulse.mp4"},{"trashed":"/home/lucas/.local/share/vifm/Trash/000_screencast-20-11-11_07-52-18.mp4","original":"/home/lucas/screencast-20-11-11_07-52-18.mp4"},{"trashed":"/home/lucas/.local/share/vifm/Trash/000_screencast-201110-1122-35.mp4","original":"/home/lucas/screencast-201110-1122-35.mp4"},{"trashed":"/home/lucas/.local/share/vifm/Trash/000_screencast-201110-1128-16.mp4","original":"/home/lucas/screencast-201110-1128-16.mp4"},{"trashed":"/home/lucas/.local/share/vifm/Trash/000_screencast-201110-1225-42.mp4","original":"/home/lucas/screencast-201110-1225-42.mp4"},{"trashed":"/home/lucas/.local/share/vifm/Trash/000_screencast-201110-1229-34.mp4","original":"/home/lucas/screencast-201110-1229-34.mp4"},{"trashed":"/home/lucas/.local/share/vifm/Trash/000_screencast-201111-0709-02.mp4","original":"/home/lucas/screencast-201111-0709-02.mp4"},{"trashed":"/home/lucas/.local/share/vifm/Trash/000_screencast-201111-0714-45.mp4","original":"/home/lucas/screencast-201111-0714-45.mp4"},{"trashed":"/home/lucas/.local/share/vifm/Trash/000_screencast-201111-0725-14.mp4","original":"/home/lucas/screencast-201111-0725-14.mp4"},{"trashed":"/home/lucas/.local/share/vifm/Trash/000_screencast-201111-0726-05.mp4","original":"/home/lucas/screencast-201111-0726-05.mp4"},{"trashed":"/home/lucas/.local/share/vifm/Trash/000_screencast-201111-0728-19.mp4","original":"/home/lucas/screencast-201111-0728-19.mp4"},{"trashed":"/home/lucas/.local/share/vifm/Trash/000_screencast-201111-0732-32.mp4","original":"/home/lucas/screencast-201111-0732-32.mp4"},{"trashed":"/home/lucas/.local/share/vifm/Trash/000_screencast-201111-0733-52.mp4","original":"/home/lucas/screencast-201111-0733-52.mp4"},{"trashed":"/home/lucas/.local/share/vifm/Trash/000_screencast-2020-11-11_07-59-04.mp4","original":"/home/lucas/screencast-2020-11-11_07-59-04.mp4"},{"trashed":"/home/lucas/.local/share/vifm/Trash/000_screencast-2020-11-11_08-09-18.mp4","original":"/home/lucas/screencast-2020-11-11_08-09-18.mp4"},{"trashed":"/home/lucas/.local/share/vifm/Trash/000_screencast-2020-11-11_08-16-22.mp4","original":"/home/lucas/screencast-2020-11-11_08-16-22.mp4"},{"trashed":"/home/lucas/.local/share/vifm/Trash/000_screencast-2020-11-11_08-17-17.mp4","original":"/home/lucas/screencast-2020-11-11_08-17-17.mp4"},{"trashed":"/home/lucas/.local/share/vifm/Trash/000_screencast-2020-11-11_08-18-06.mp4","original":"/home/lucas/screencast-2020-11-11_08-18-06.mp4"},{"trashed":"/home/lucas/.local/share/vifm/Trash/000_screencast-2020-11-11_08-18-55.mp4","original":"/home/lucas/screencast-2020-11-11_08-18-55.mp4"},{"trashed":"/home/lucas/.local/share/vifm/Trash/000_screencast-2020-11-11_08-19-44.mp4","original":"/home/lucas/screencast-2020-11-11_08-19-44.mp4"},{"trashed":"/home/lucas/.local/share/vifm/Trash/000_screencast-2020-11-11_08-20-11.mp4","original":"/home/lucas/screencast-2020-11-11_08-20-11.mp4"},{"trashed":"/home/lucas/.local/share/vifm/Trash/000_screencast-2020-11-11_08-22-38.mp4","original":"/home/lucas/screencast-2020-11-11_08-22-38.mp4"},{"trashed":"/home/lucas/.local/share/vifm/Trash/000_screencast-2020-11-11_08-23-31.mp4","original":"/home/lucas/screencast-2020-11-11_08-23-31.mp4"},{"trashed":"/home/lucas/.local/share/vifm/Trash/000_screencast-2020-11-11_08-23-50.mp4","original":"/home/lucas/screencast-2020-11-11_08-23-50.mp4"},{"trashed":"/home/lucas/.local/share/vifm/Trash/000_screencast-2020-11-11_08-24-46.mp4","original":"/home/lucas/screencast-2020-11-11_08-24-46.mp4"},{"trashed":"/home/lucas/.local/share/vifm/Trash/000_screencast-2020-11-11_08-25-57.mp4","original":"/home/lucas/screencast-2020-11-11_08-25-57.mp4"},{"trashed":"/home/lucas/.local/share/vifm/Trash/000_screencast-2020-11-11_08-26-17.mp4","original":"/home/lucas/screencast-2020-11-11_08-26-17.mp4"},{"trashed":"/home/lucas/.local/share/vifm/Trash/000_screencast-2020-11-11_08-28-45.mp4","original":"/home/lucas/screencast-2020-11-11_08-28-45.mp4"},{"trashed":"/home/lucas/.local/share/vifm/Trash/000_screencast-2020-11-11_08-30-28.mp4","original":"/home/lucas/screencast-2020-11-11_08-30-28.mp4"},{"trashed":"/home/lucas/.local/share/vifm/Trash/000_screencast-2020-11-11_08-31-46.mp4","original":"/home/lucas/screencast-2020-11-11_08-31-46.mp4"},{"trashed":"/home/lucas/.local/share/vifm/Trash/000_screencast-2020-11-11_08-33-25.mp4","original":"/home/lucas/screencast-2020-11-11_08-33-25.mp4"},{"trashed":"/home/lucas/.local/share/vifm/Trash/000_screencast-2020-11-11_08-38-21.mp4","original":"/home/lucas/screencast-2020-11-11_08-38-21.mp4"},{"trashed":"/home/lucas/.local/share/vifm/Trash/000_screencast-2020-11-11_08-50-09.mp4","original":"/home/lucas/screencast-2020-11-11_08-50-09.mp4"},{"trashed":"/home/lucas/.local/share/vifm/Trash/000_screencast-2020-11-11_08-52-27.mp4","original":"/home/lucas/screencast-2020-11-11_08-52-27.mp4"},{"trashed":"/home/lucas/.local/share/vifm/Trash/000_2020-11-04-205558_2001x1404_scrot.png","original":"/home/lucas/scrot/2020-11-04-205558_2001x1404_scrot.png"},{"trashed":"/home/lucas/.local/share/vifm/Trash/000_2020-11-04-205611_1953x1688_scrot.png","original":"/home/lucas/scrot/2020-11-04-205611_1953x1688_scrot.png"},{"trashed":"/home/lucas/.local/share/vifm/Trash/000_2020-11-04-205651_1964x1400_scrot.png","original":"/home/lucas/scrot/2020-11-04-205651_1964x1400_scrot.png"},{"trashed":"/home/lucas/.local/share/vifm/Trash/000_2020-11-04-205715_1016x1460_scrot.png","original":"/home/lucas/scrot/2020-11-04-205715_1016x1460_scrot.png"},{"trashed":"/home/lucas/.local/share/vifm/Trash/000_2020-11-06-122825_784x216_scrot.png","original":"/home/lucas/scrot/2020-11-06-122825_784x216_scrot.png"},{"trashed":"/home/lucas/.local/share/vifm/Trash/000_src","original":"/home/lucas/src"},{"trashed":"/home/lucas/.local/share/vifm/Trash/000_teste.mp4","original":"/home/lucas/teste.mp4"},{"trashed":"/home/lucas/.local/share/vifm/Trash/000_video (1).mp4","original":"/home/lucas/video (1).mp4"},{"trashed":"/home/lucas/.local/share/vifm/Trash/000_video (3).mp4","original":"/home/lucas/video (3).mp4"},{"trashed":"/home/lucas/.local/share/vifm/Trash/001_video (3).mp4","original":"/home/lucas/video (3).mp4"},{"trashed":"/home/lucas/.local/share/vifm/Trash/000_000_.Xauthority","original":"/mnt/files/.vifm-Trash-0/000_.Xauthority"},{"trashed":"/home/lucas/.local/share/vifm/Trash/000_000_.octave_hist","original":"/mnt/files/.vifm-Trash-0/000_.octave_hist"},{"trashed":"/home/lucas/.local/share/vifm/Trash/000_000_.rtorrent.rc","original":"/mnt/files/.vifm-Trash-0/000_.rtorrent.rc"},{"trashed":"/home/lucas/.local/share/vifm/Trash/000_000_.viminfo","original":"/mnt/files/.vifm-Trash-0/000_.viminfo"},{"trashed":"/home/lucas/.local/share/vifm/Trash/000_000_.viminfo.tmp","original":"/mnt/files/.vifm-Trash-0/000_.viminfo.tmp"},{"trashed":"/home/lucas/.local/share/vifm/Trash/000_000_.zcompdump","original":"/mnt/files/.vifm-Trash-0/000_.zcompdump"},{"trashed":"/home/lucas/.local/share/vifm/Trash/000_000_Dhciolfi","original":"/mnt/files/.vifm-Trash-0/000_Dhciolfi"},{"trashed":"/home/lucas/.local/share/vifm/Trash/000_000_InstagramPhotos_XJ9Y2PQ6WQ","original":"/mnt/files/.vifm-Trash-0/000_InstagramPhotos_XJ9Y2PQ6WQ"},{"trashed":"/home/lucas/.local/share/vifm/Trash/000_000_flutter","original":"/mnt/files/.vifm-Trash-0/000_flutter"},{"trashed":"/home/lucas/.local/share/vifm/Trash/000_000_octave-workspace","original":"/mnt/files/.vifm-Trash-0/000_octave-workspace"},{"trashed":"/home/lucas/.local/share/vifm/Trash/000_000_session","original":"/mnt/files/.vifm-Trash-0/000_session"},{"trashed":"/home/lucas/.local/share/vifm/Trash/000_000_videos","original":"/mnt/files/.vifm-Trash-0/000_videos"},{"trashed":"/home/lucas/.local/share/vifm/Trash/000_000_watch","original":"/mnt/files/.vifm-Trash-0/000_watch"},{"trashed":"/home/lucas/.local/share/vifm/Trash/000_node_modules","original":"/mnt/files/Lucas/Desktop/Chronos/node_modules"},{"trashed":"/home/lucas/.local/share/vifm/Trash/001_System Volume Information","original":"/mnt/files/System Volume Information"},{"trashed":"/home/lucas/.local/share/vifm/Trash/001_scripts.txt","original":"/mnt/files/arch/lucas/scripts/scripts.txt"},{"trashed":"/home/lucas/.local/share/vifm/Trash/000_.vimrc","original":"/mnt/hd/.vimrc"},{"trashed":"/home/lucas/.local/share/vifm/Trash/000_System Volume Information","original":"/mnt/hd/System Volume Information"},{"trashed":"/home/lucas/.local/share/vifm/Trash/000_files","original":"/mnt/hd/files"},{"trashed":"/home/lucas/.local/share/vifm/Trash/000_matriz","original":"/mnt/hd/matriz"},{"trashed":"/mnt/hd/.vifm-Trash-1000/000_.DS_Store","original":"/mnt/hd/projeto/.DS_Store"},{"trashed":"/mnt/hd/.vifm-Trash-1000/000_._Monografia_TCC_UEMG___J_nior_Conquista.pdf","original":"/mnt/hd/projeto/._Monografia_TCC_UEMG___J_nior_Conquista.pdf"},{"trashed":"/mnt/hd/.vifm-Trash-1000/000_._Projeto Chonus.docx","original":"/mnt/hd/projeto/._Projeto Chonus.docx"},{"trashed":"/mnt/hd/.vifm-Trash-1000/000_._Template_CILAMCE2019_LaTeX_Full_Paper.pdf","original":"/mnt/hd/projeto/._Template_CILAMCE2019_LaTeX_Full_Paper.pdf"},{"trashed":"/mnt/hd/.vifm-Trash-1000/000_._analise2.0.txt","original":"/mnt/hd/projeto/._analise2.0.txt"},{"trashed":"/mnt/hd/.vifm-Trash-1000/000_._tiago.html","original":"/mnt/hd/projeto/._tiago.html"}],"marks":{"1":{"dir":"/home/lucas/Engenharia_de_Computacao/1_periodo","file":"..","ts":1601458588},"2":{"dir":"/home/lucas/Engenharia_de_Computacao/2_periodo","file":"..","ts":1601458592},"3":{"dir":"/home/lucas/Engenharia_de_Computacao/3_periodo","file":"..","ts":1601458634},"c":{"dir":"/home/lucas/.config","file":"..","ts":1601458657},"d":{"dir":"/home/lucas/Downloads","file":"..","ts":1601570157},"f":{"dir":"/mnt/files","file":"..","ts":1602813483},"h":{"dir":"/home/lucas/","file":"..","ts":1601481302},"k":{"dir":"/home/lucas/Engenharia_de_Computacao/3_periodo/AOCO","file":"Data_Path_-_Lucas_Martins_Soares.dig","ts":1604271257},"o":{"dir":"/opt","file":"..","ts":1601458573}},"bmarks":{},"cmd-hist":[{"text":"cd /home/lucas/","ts":1602720405},{"text":"delbmarks!","ts":1602720405},{"text":"delm!","ts":1602720405},{"text":"mkdir imv","ts":1602720405},{"text":"cd /mnt/files/","ts":1602720405},{"text":"!zathura CamScanner\\ 09-30-2020\\ 22.14.30.pdf","ts":1602720405},{"text":"!zathura 2020-09-10\\ at\\ 14.58.09.jpeg","ts":1602720405},{"text":"!zathura 30e99b818f574c5ea1a4d59c09b18cbf.jpg","ts":1602720405},{"text":"!ffmpeg -i INPUT.mkv -c:v libx265 -preset ultrafast -x265-params lossless=1 OUTPUT.mkv","ts":1602720405},{"text":"!ffmpeg -i listas.mp4 -c:v libx265 -preset ultrafast -x265-params listas2.mp4","ts":1602720405},{"text":"!ffmpeg -i listas.mp4 -c:v libx265 -preset ultrafast -x265-params lossless=1 listas2.mp4","ts":1602720405},{"text":"!ffmplay OneDrive\\ for\\ Business.mp4","ts":1602720405},{"text":"!ffplay OneDrive\\ for\\ Business.mp4","ts":1602720405},{"text":"!code .","ts":1602720405},{"text":"touch .lldbinit","ts":1602720405},{"text":"!unzip Algoritmo_Recomenda√ß√£o\\ .zip","ts":1602720405},{"text":"shell","ts":1602720405},{"text":"!tar xvpf servo-latest.tar.gz","ts":1602720405},{"text":"mkdir gtk","ts":1602720405},{"text":"!libreoffice --infilter==\"writer_pdf_import\" --headless \\","ts":1602720405},{"text":"!./hello-world-gtk","ts":1602720405},{"text":"mkdir novos","ts":1602726129},{"text":"!grep -R \"C√°lculo\" *","ts":1602728022},{"text":"!find -R -name \"C√°lculo\" *","ts":1602728022},{"text":"!find -r -name \"C√°lculo\" *","ts":1602728022},{"text":"!find -name \"C√°lculo\" .","ts":1602728022},{"text":"!find . -name \"C√°lculo\"","ts":1602728022},{"text":"mkdir prova 1","ts":1602728022},{"text":"mkdir prova_1","ts":1602728022},{"text":"mkdir prova_2","ts":1602728022},{"text":"mkdir slides","ts":1602813195},{"text":"touch matriz_de_fatora√ß√£o.c","ts":1602976252},{"text":"cd /home/lucas/Engenharia_de_Computacao/3_periodo/FISICA2/Teams","ts":1602976252},{"text":"mkdir Documents","ts":1602988836},{"text":"w","ts":1602990336},{"text":"touch config","ts":1602996424},{"text":"cd /opt","ts":1603048597},{"text":"mkdir aula2_dinamica","ts":1603125026},{"text":"mkdir resumos","ts":1603218110},{"text":"!unzip master_Li_high.zip","ts":1603393320},{"text":"touch dracula.js","ts":1603417352},{"text":"! vim dracula.js","ts":1603417352},{"text":"! etags -R","ts":1603458524},{"text":"! etags *.hpp *.cpp","ts":1603458524},{"text":"! emacs main.cpp &","ts":1603458524},{"text":"! vim main.cpp &","ts":1603464686},{"text":"! vim main.cpp","ts":1603464686},{"text":"! emacs main.cpp","ts":1603470608},{"text":"mkdir C++","ts":1603477364},{"text":"!sudo vim bl-brightness","ts":1603483793},{"text":"wq","ts":1603484207},{"text":"help view","ts":1603485272},{"text":"help ","ts":1603485272},{"text":"cd /etc/local.d","ts":1603485272},{"text":"cd /etc","ts":1603485272},{"text":"mkdir etc-udev-rules.d","ts":1603485272},{"text":"mkdir etc-local.d","ts":1603485272},{"text":"mkdir usr-share-X11-xkb-symbols","ts":1603490825},{"text":"mkdir dotfiles","ts":1603490825},{"text":"mkdir home","ts":1603490825},{"text":"mkdir .config","ts":1603490825},{"text":"empty","ts":1603497481},{"text":"mkdir files","ts":1603506796},{"text":"mkdir fontconfig","ts":1603553838},{"text":"touch fonts.conf","ts":1603553838},{"text":"! etags *.cpp *.hpp","ts":1603575276},{"text":"mkdir src","ts":1603576680},{"text":"! sudo vim ext","ts":1603576680},{"text":"touch UsuariosSimilares.hpp","ts":1603578485},{"text":"touch UsuariosSimilares.cpp","ts":1603578485},{"text":"touch Fila.cpp","ts":1603591062},{"text":"touch Pilha.cpp","ts":1603591062},{"text":"mkdir home-user-.vim-after-ftplugin","ts":1603591062},{"text":"touch UsuariosSemelhantes.hpp","ts":1603594493},{"text":"touch UsuariosSemelhantes.cpp","ts":1603594493},{"text":"touch Lista.cpp","ts":1603647445},{"text":"!etags *","ts":1603647445},{"text":"touch teste.c","ts":1603742983},{"text":"zsh","ts":1603752958},{"text":"nnoremap yn :!printf '%%s' %c|sed \"s/\\..*//\"|xclip -selection clipboard %i<cr>","ts":1603841798},{"text":"!zsh","ts":1603842785},{"text":"pwd","ts":1603998937},{"text":"touch tokenizer.cpp","ts":1604067247},{"text":"mkdir Torrent","ts":1604184990},{"text":"touch leitura_complementar.txt","ts":1604241701},{"text":"mkdir 3-metodos_de_ordenacao","ts":1604273225},{"text":"mkdir exercicios","ts":1604276172},{"text":"mkdir Exercicio","ts":1604276172},{"text":"mkdir Livros","ts":1604276172},{"text":"mkdir IAS","ts":1604276172},{"text":"mkdir","ts":1604276172},{"text":"mkdir Data_Path_-_Lucas_Martins_Soares","ts":1604276172},{"text":"mkdir Interconex√£o de barramento","ts":1604426649},{"text":"mkdir \"Interconex√£o de barramento\"","ts":1604426649},{"text":"mkdir ","ts":1604715126},{"text":"mkdir prova","ts":1604715126},{"text":"touch fsr","ts":1604956723},{"text":"sort ","ts":1604972867},{"text":"q","ts":1605018075},{"text":"sh","ts":1605047985}],"search-hist":[{"text":"vfm","ts":1602720405},{"text":"profile","ts":1602720405},{"text":".conf","ts":1602720405},{"text":"libre","ts":1602720405},{"text":"confi","ts":1602720405},{"text":"dow","ts":1602720405},{"text":".xini","ts":1602720405},{"text":".xin","ts":1602720405},{"text":"zsh","ts":1602720405},{"text":"**/calculo","ts":1602728022},{"text":"config","ts":1602978875},{"text":"conf","ts":1602993777},{"text":"nvim","ts":1602998469},{"text":"us","ts":1603292121},{"text":"emacs","ts":1603402940},{"text":".emacs","ts":1603404974},{"text":".ema","ts":1603404974},{"text":"dm","ts":1603481624},{"text":"local","ts":1603485272},{"text":"udev","ts":1603485272},{"text":"ala","ts":1603566832},{"text":"inpu","ts":1603575276},{"text":"font","ts":1603575276},{"text":"vim","ts":1603591062},{"text":"imv","ts":1603683814},{"text":"xre","ts":1603730340},{"text":"vimrc","ts":1603745889},{"text":"main","ts":1604175661},{"text":"xin","ts":1604276172},{"text":"xini","ts":1604337125},{"text":"vifm","ts":1604409328},{"text":"mpv","ts":1604512514},{"text":"za","ts":1604598169},{"text":"ff","ts":1604956723},{"text":".screen","ts":1604958965},{"text":"lu","ts":1605042576},{"text":"scri","ts":1605094557}],"prompt-hist":[{"text":"Lista.hpp","ts":1603647445},{"text":"home-user","ts":1603683814},{"text":".vim-after-ftplugin","ts":1603683814},{"text":"2020-10-26","ts":1603719657},{"text":"ratings_Amazon_Instant_Video.csv","ts":1603742983},{"text":"new.txt","ts":1603745384},{"text":"newUser.cpp","ts":1603745384},{"text":".vimrc2","ts":1603745889},{"text":".vimrc","ts":1603745889},{"text":"produtos.txt","ts":1603752958},{"text":"notas.txt","ts":1603752958},{"text":"usuario.txt","ts":1603752958},{"text":"10000.csv","ts":1603752958},{"text":"10000_amazon","ts":1603752958},{"text":"amazon_usuario","ts":1603752958},{"text":"amazon_10000.csv","ts":1603752958},{"text":"pequeno_usuario.txt","ts":1603752958},{"text":"pequeno_matriz.txt","ts":1603752958},{"text":"pequeno.txt","ts":1603760644},{"text":"2020-10-28","ts":1603890577},{"text":"2020-10-20_aula_10","ts":1603890577},{"text":"2020-10-20_pratica_09","ts":1603890577},{"text":"teste.cpp","ts":1603998397},{"text":"backup","ts":1603998937},{"text":"0Tokenizer.cpp","ts":1604062724},{"text":"Laborat√≥rio_de_Programa√ß√£o","ts":1604062724},{"text":"Tokenizer2.cpp","ts":1604062724},{"text":"Tokenizer2.hpp","ts":1604062724},{"text":"Fila1.cpp","ts":1604062724},{"text":"Fila1.hpp","ts":1604062724},{"text":"TokenizacÃßaÃÉo + Template2","ts":1604067247},{"text":"main.cpp","ts":1604067247},{"text":"teste","ts":1604067247},{"text":"tokenizer.h","ts":1604067247},{"text":"tokenizer.hpp","ts":1604067247},{"text":"Tokenizer.cpp","ts":1604067247},{"text":"0-analise_assintotica","ts":1604273225},{"text":"1-estruturas_estaticas","ts":1604273225},{"text":"2-estruturas_dinamicas","ts":1604273225},{"text":"scratch.pdf","ts":1604273225},{"text":"algoritmo_de_recomendacao.pdf","ts":1604273225},{"text":"Aula.pdf","ts":1604273225},{"text":"Contadores","ts":1604276172},{"text":"Exercicios","ts":1604276172},{"text":"Data_Path_-_Lucas_Martins_Soares.pdf","ts":1604276172},{"text":"Data_Path_-_Lucas_Martins_Soares.dig","ts":1604276172},{"text":"Data_Path","ts":1604276172},{"text":"man_digital.pdf","ts":1604276172},{"text":"arquitetura-e-organizaccedilatildeo-de-computadores-8ordf-edpdf.pdf","ts":1604334380},{"text":"arquitetura-e-organizaccedilatildeo-de-computadores-8ed.pdf","ts":1604334380},{"text":"Arquitetura_Organizacao_Computadores_5ed.pdf","ts":1604334380},{"text":"arquitetura-e-organizacao-de-computadores-8ed.pdf","ts":1604334380},{"text":"Arquitetura-e-organizacao-de-computadores-8ed.pdf","ts":1604334380},{"text":"Interconex√£o de barramento.md","ts":1604426649},{"text":"Interconex√£o_de_barramento_-_Lucas_Martins_Soares.pdf","ts":1604426649},{"text":"FPHeapMax.hpp","ts":1604437863},{"text":"Ordenacao.hpp","ts":1604437863},{"text":"2020-09-30_Quest√£o 2 Prova.mp4","ts":1604512514},{"text":"2020-10-30.mp4","ts":1604512514},{"text":"2020-11-04","ts":1604512514},{"text":"2020-10-23","ts":1604512514},{"text":"2020-10-21.mp4","ts":1604512514},{"text":"2020-10-15.webm","ts":1604512514},{"text":"Edpuzzle(1).webm","ts":1604512514},{"text":"2020-10-27.webm","ts":1604512514},{"text":"2020-10-22.webm","ts":1604512514},{"text":"2020-10-20.mkv","ts":1604512514},{"text":"2020-11-10.webm","ts":1604512514},{"text":"2020-10-02_correcao_prova1.mp4","ts":1604512514},{"text":"2020-10-06-01_corrente_e_resistencia.webm","ts":1604512514},{"text":"2020-10-06-02_capacitores_3.webm","ts":1604535292},{"text":"2020-09-29_capacitores_2.webm","ts":1604535292},{"text":"2020-10-14-01_forca_eletromotriz","ts":1604535292},{"text":"2020-10-14-02","ts":1604535292},{"text":"2020-10-14-02_circuitos_corrente_continua","ts":1604535292},{"text":"2020-10-15_circuitos_RC","ts":1604535292},{"text":"2020-10-22_campos_magneticos","ts":1604535292},{"text":"2020-10-27_movimento_particulas_carregadas_campo_magnetico","ts":1604535292},{"text":"2020-11-10_torque_espiras_efeito_hall","ts":1604535292},{"text":"2020-10-20_campo_magnetico_1","ts":1604535292},{"text":"2020-11-04_____________________________________________PROVA_2__","ts":1604535292},{"text":"2020-11-04______________________________________________PROVA_2__.mp4","ts":1604535292},{"text":"26-Circuitos_de_Corrente_Continua-2.png","ts":1604536132},{"text":"26-Circuitos_de_Corrente_Continua-3","ts":1604712272},{"text":"Prova_2_-_Lucas_Martins_Soares","ts":1604715431},{"text":"2020-11-05.mp4","ts":1604887342},{"text":"2020-10-29.mp4","ts":1604887342},{"text":"Etapa_2","ts":1604887342},{"text":"TT01","ts":1604887342},{"text":"2020-10-22","ts":1604972867},{"text":"2020-10-29","ts":1604972867},{"text":"2020-11-05","ts":1604972867},{"text":"2020-11-05____caiu.mp4","ts":1605042576},{"text":"video.mp4","ts":1605042576},{"text":"2020-11-03","ts":1605042576},{"text":"2020-11-03.mp4","ts":1605042576},{"text":"2020-11-03_pratica.mp4","ts":1605042576},{"text":"2020-11-03_teorica","ts":1605042576},{"text":"video","ts":1605094557},{"text":"2020-11-10","ts":1605094557}],"regs":{"\"":["/home/lucas/scripts/fsr"]},"dir-stack":[],"use-term-multiplexer":false}